{
  "solution": {
    "@embroider/addon-dev": {
      "oldVersion": "8.3.0"
    },
    "@embroider/addon-shim": {
      "oldVersion": "1.10.2"
    },
    "@embroider/babel-loader-9": {
      "oldVersion": "4.0.0"
    },
    "@embroider/broccoli-side-watch": {
      "oldVersion": "1.1.0"
    },
    "@embroider/compat": {
      "impact": "patch",
      "oldVersion": "4.1.16",
      "newVersion": "4.1.17",
      "tagName": "latest",
      "constraints": [
        {
          "impact": "patch",
          "reason": "Appears in changelog section :bug: Bug Fix"
        }
      ],
      "pkgJSONPath": "./packages/compat/package.json"
    },
    "@embroider/config-meta-loader": {
      "oldVersion": "1.0.0"
    },
    "@embroider/core": {
      "oldVersion": "4.4.7"
    },
    "@embroider/hbs-loader": {
      "oldVersion": "4.0.0"
    },
    "@embroider/legacy-inspector-support": {
      "oldVersion": "0.1.3"
    },
    "@embroider/macros": {
      "oldVersion": "1.20.2"
    },
    "@embroider/reverse-exports": {
      "oldVersion": "0.2.0"
    },
    "@embroider/router": {
      "oldVersion": "3.0.6"
    },
    "@embroider/shared-internals": {
      "oldVersion": "3.0.2"
    },
    "@embroider/template-tag-codemod": {
      "oldVersion": "1.3.6"
    },
    "@embroider/vite": {
      "impact": "patch",
      "oldVersion": "1.7.1",
      "newVersion": "1.7.2",
      "tagName": "latest",
      "constraints": [
        {
          "impact": "patch",
          "reason": "Appears in changelog section :house: Internal"
        }
      ],
      "pkgJSONPath": "./packages/vite/package.json"
    }
  },
  "description": "## Release (2026-03-29)\n\n* @embroider/compat 4.1.17 (patch)\n* @embroider/vite 1.7.2 (patch)\n\n#### :bug: Bug Fix\n* `@embroider/compat`\n  * [#2695](https://github.com/embroider-build/embroider/pull/2695) Conditional file writes for Ember modules ([@NullVoxPopuli](https://github.com/NullVoxPopuli))\n  * [#2696](https://github.com/embroider-build/embroider/pull/2696) Fix paths check to use existence rather than value-as-key lookup ([@NullVoxPopuli-ai-agent](https://github.com/NullVoxPopuli-ai-agent))\n\n#### :house: Internal\n* `@embroider/vite`\n  * [#2693](https://github.com/embroider-build/embroider/pull/2693) Fix CI: use caret range for rolldown devDependency ([@NullVoxPopuli-ai-agent](https://github.com/NullVoxPopuli-ai-agent))\n\n#### Committers: 2\n- @NullVoxPopuli's reduced-access machine account for AI usage ([@NullVoxPopuli-ai-agent](https://github.com/NullVoxPopuli-ai-agent))\n- [@NullVoxPopuli](https://github.com/NullVoxPopuli)\n"
}
